onany/__init__.py
onany/manager.py
onany/web.py
onany-0.2.0.dist-info/LICENSE
onany-0.2.0.dist-info/METADATA
onany-0.2.0.dist-info/WHEEL
onany-0.2.0.dist-info/top_level.txt
onany-0.2.0.dist-info/RECORD
